kick/__init__.py
kick/config.py
kick/logging.py
tests/__init__.py
kick-1.1.0.dist-info/LICENSE-APACHE
kick-1.1.0.dist-info/LICENSE-MIT
kick-1.1.0.dist-info/METADATA
kick-1.1.0.dist-info/WHEEL
kick-1.1.0.dist-info/top_level.txt
kick-1.1.0.dist-info/RECORD
