Metadata-Version: 2.1
Name: kick
Version: 1.1.0
Summary: UNKNOWN
Home-page: https://github.com/alin23/kick
Author: Alin Panaitiu
Author-email: alin.p32@gmail.com
Maintainer: Alin Panaitiu
Maintainer-email: alin.p32@gmail.com
License: MIT/Apache-2.0
Platform: UNKNOWN
Classifier: Development Status :: 4 - Beta
Classifier: Intended Audience :: Developers
Classifier: License :: OSI Approved :: MIT License
Classifier: License :: OSI Approved :: Apache Software License
Classifier: Natural Language :: English
Classifier: Operating System :: OS Independent
Classifier: Programming Language :: Python :: 3.5
Classifier: Programming Language :: Python :: 3.6
Classifier: Programming Language :: Python :: Implementation :: CPython
Classifier: Programming Language :: Python :: Implementation :: PyPy
Requires-Dist: addict
Requires-Dist: toml
Requires-Dist: daiquiri
Requires-Dist: pint
Requires-Dist: first
